qigkernels/__init__.py
qigkernels/basin.py
qigkernels/basin_sync.py
qigkernels/constants.py
qigkernels/constellation.py
qigkernels/kernel.py
qigkernels/layer.py
qigkernels/metrics.py
qigkernels/pure_kernel_template.py
qigkernels/rel_coupling.py
qigkernels/router.py
qigkernels/storage.py
qigkernels-0.1.0.dist-info/METADATA
qigkernels-0.1.0.dist-info/WHEEL
qigkernels-0.1.0.dist-info/top_level.txt
qigkernels-0.1.0.dist-info/RECORD
