Metadata-Version: 2.4
Name: qigkernels
Version: 0.1.0
Summary: Geometric kernel and constellation library for QIG.
Requires-Python: >=3.11
Requires-Dist: torch>=2.2
Requires-Dist: pydantic>=2.5
Requires-Dist: numpy>=1.24
Provides-Extra: dev
Requires-Dist: pytest; extra == "dev"
Requires-Dist: mypy; extra == "dev"
Requires-Dist: ruff; extra == "dev"
Requires-Dist: pre-commit; extra == "dev"
